dashbase/__init__.py
dashbase/auth.py
dashbase/client.py
dashbase/request.py
dashbase/response.py
dashbase/utils.py
dashbase_sdk-0.0.10.dist-info/METADATA
dashbase_sdk-0.0.10.dist-info/RECORD
dashbase_sdk-0.0.10.dist-info/WHEEL
dashbase_sdk-0.0.10.dist-info/top_level.txt
