Metadata-Version: 2.1
Name: dashbase-sdk
Version: 0.0.10
Summary: Dashbase python sdk
Home-page: UNKNOWN
Author: peter wang
Author-email: peter@dashbase.io
License: UNKNOWN
Platform: UNKNOWN
Requires-Dist: requests
Requires-Dist: schematics
Requires-Dist: click
